cifar_10_model/VERSION
cifar_10_model/__init__.py
cifar_10_model/model.py
cifar_10_model/predict.py
cifar_10_model/train.py
cifar_10_model/config/__init__.py
cifar_10_model/config/config.py
cifar_10_model/processing/__init__.py
cifar_10_model/processing/data_management.py
cifar_10_model/processing/errors.py
cifar_10_model/processing/preprocessors.py
cifar_10_model/testing_images/__init__.py
cifar_10_model/trained_models/__init__.py
cifar_10_model/trained_models/cnn_model.h5
cifar_10_model-7.4.0.dist-info/METADATA
cifar_10_model-7.4.0.dist-info/WHEEL
cifar_10_model-7.4.0.dist-info/top_level.txt
cifar_10_model-7.4.0.dist-info/RECORD
