Metadata-Version: 2.1
Name: cifar-10-model
Version: 7.4.0
Summary: Image Classifier for CIFAR 10 Dataset
Home-page: https://github.com/sgudiduri/Projects/tree/main/research_to_deployment/cifar10/production
Author: Siddharth Gudiduri
Author-email: siddu.gemeni@gmail.com
License: BSD-3
Classifier: License :: OSI Approved :: MIT License
Classifier: Programming Language :: Python
Classifier: Programming Language :: Python :: 3
Classifier: Programming Language :: Python :: 3.6
Classifier: Programming Language :: Python :: 3.7
Classifier: Programming Language :: Python :: 3.8
Classifier: Programming Language :: Python :: 3.9
Classifier: Programming Language :: Python :: Implementation :: CPython
Classifier: Programming Language :: Python :: Implementation :: PyPy
Requires-Python: >=3.8.15
Requires-Dist: setuptools (==65.5.0)
Requires-Dist: wheel (==0.37.1)
Requires-Dist: numpy (==1.23.5)
Requires-Dist: scikit-learn (==1.1.3)
Requires-Dist: tensorflow-cpu (==2.10.0)
Requires-Dist: opencv-python (==4.7.0.68)
Requires-Dist: h5py (==3.7.0)
Requires-Dist: pytest (==7.1.2)
